yaml-stubs/METADATA.toml
yaml-stubs/__init__.pyi
yaml-stubs/_yaml.pyi
yaml-stubs/composer.pyi
yaml-stubs/constructor.pyi
yaml-stubs/cyaml.pyi
yaml-stubs/dumper.pyi
yaml-stubs/emitter.pyi
yaml-stubs/error.pyi
yaml-stubs/events.pyi
yaml-stubs/loader.pyi
yaml-stubs/nodes.pyi
yaml-stubs/parser.pyi
yaml-stubs/py.typed
yaml-stubs/reader.pyi
yaml-stubs/representer.pyi
yaml-stubs/resolver.pyi
yaml-stubs/scanner.pyi
yaml-stubs/serializer.pyi
yaml-stubs/tokens.pyi
types_PyYAML-6.0.12.20241221.dist-info/LICENSE
types_PyYAML-6.0.12.20241221.dist-info/METADATA
types_PyYAML-6.0.12.20241221.dist-info/WHEEL
types_PyYAML-6.0.12.20241221.dist-info/top_level.txt
types_PyYAML-6.0.12.20241221.dist-info/RECORD
